autoupgrader/__init__.py
autoupgrader/updater.py
autoupgrader-0.1.2.dist-info/licenses/LICENSE
autoupgrader-0.1.2.dist-info/METADATA
autoupgrader-0.1.2.dist-info/WHEEL
autoupgrader-0.1.2.dist-info/top_level.txt
autoupgrader-0.1.2.dist-info/RECORD
