Metadata-Version: 2.4
Name: autoupgrader
Version: 0.1.2
Summary: A library for automatic Python updates
Home-page: https://github.com/Pytholearn/autoupgrader
Author: HaZaRd
Author-email: police123456789ilia@gmail.com
Classifier: Programming Language :: Python :: 3
Classifier: License :: OSI Approved :: MIT License
Classifier: Operating System :: OS Independent
Requires-Python: >=3.6
License-File: LICENSE
Requires-Dist: gitpython
Dynamic: author
Dynamic: author-email
Dynamic: classifier
Dynamic: description
Dynamic: description-content-type
Dynamic: home-page
Dynamic: license-file
Dynamic: requires-dist
Dynamic: requires-python
Dynamic: summary
